banhammer/__init__.py
banhammer/frames.json
banhammer/generator.py
banhammer/assets/Bungee-LICENSE.txt
banhammer/assets/Bungee-Regular.ttf
banhammer/assets/DejaVu-LICENSE.txt
banhammer/assets/Tetsubin-LICENSE.txt
banhammer/assets/twitter-color-emoji-LICENSE.txt
banhammer/frames/frame00.gif
banhammer/frames/frame01.gif
banhammer/frames/frame02.gif
banhammer/frames/frame03.gif
banhammer/frames/frame04.gif
banhammer/frames/frame05.gif
banhammer/frames/frame06.gif
banhammer/frames/frame07.gif
banhammer/frames/frame08.gif
banhammer/frames/frame09.gif
banhammer/frames/frame10.gif
banhammer/frames/frame11.gif
banhammer/frames/frame12.gif
banhammer/frames/frame13.gif
banhammer/frames/frame14.gif
banhammer/frames/frame15.gif
banhammer/frames/frame16.gif
banhammer/frames/frame17.gif
banhammer/frames/frame18.gif
banhammer/frames/frame19.gif
banhammer/frames/frame20.gif
banhammer/frames/frame21.gif
banhammer/frames/frame22.gif
banhammer/frames/frame23.gif
banhammer/frames/frame24.gif
banhammer/frames/frame25.gif
banhammer/frames/frame26.gif
banhammer/frames/frame27.gif
banhammer/frames/frame28.gif
banhammer/frames/frame29.gif
banhammer/frames/frame30.gif
banhammer/frames/frame31.gif
banhammer/frames/frame32.gif
banhammer/frames/frame33.gif
banhammer/frames/frame34.gif
banhammer/frames/frame35.gif
banhammer/frames/frame36.gif
banhammer/frames/frame37.gif
banhammer/frames/frame38.gif
banhammer/frames/frame39.gif
banhammer/frames/frame40.gif
banhammer/frames/frame41.gif
banhammer/frames/frame42.gif
banhammer/frames/frame43.gif
banhammer/frames/frame44.gif
banhammer/frames/frame45.gif
banhammer/frames/frame46.gif
banhammer/frames/frame47.gif
banhammer/frames/frame48.gif
banhammer/frames/frame49.gif
banhammer/frames/frame50.gif
banhammer/frames/frame51.gif
banhammer/frames/frame52.gif
banhammer/frames/frame53.gif
banhammer/frames/frame54.gif
banhammer/frames/frame55.gif
banhammer/frames/frame56.gif
banhammer/frames/frame57.gif
banhammer/frames/frame58.gif
banhammer-0.1.3.dist-info/LICENSE
banhammer-0.1.3.dist-info/METADATA
banhammer-0.1.3.dist-info/WHEEL
banhammer-0.1.3.dist-info/top_level.txt
banhammer-0.1.3.dist-info/RECORD
