Metadata-Version: 2.1
Name: banhammer
Version: 0.1.3
Summary: Generates GIFs based on Tom Scott's Banhammer
Home-page: https://github.com/DerpyChap/banhammer
Author: DerpyChap
Author-email: holla@derpychap.co.uk
License: ISC
License-File: LICENSE
Requires-Dist: pillow
Requires-Dist: imageio
Requires-Dist: numpy
